score_clustering/__init__.py
score_clustering/_score_clustering.py
score_clustering/cluster.py
score_clustering/point.py
test/__init__.py
test/test_clustering.py
test/test_points.py
score_clustering-0.1.4.dist-info/LICENSE
score_clustering-0.1.4.dist-info/METADATA
score_clustering-0.1.4.dist-info/WHEEL
score_clustering-0.1.4.dist-info/top_level.txt
score_clustering-0.1.4.dist-info/RECORD
