Metadata-Version: 2.1
Name: score-clustering
Version: 0.1.4
Summary: A clustering algorithm to divide points into clusters of equal score.
Home-page: https://github.com/arnauqb/score_clustering
Author: Arnau Quera-Bofarull
Author-email: arnauq@protonmail.com
License: MIT
Platform: UNKNOWN
Requires-Dist: networkx (>=2.5)
Requires-Dist: numpy (>=1.20)
Requires-Dist: scikit-learn (>=0.24)
Requires-Dist: scipy (>=1.6)
Requires-Dist: sortedcontainers (>=2.3)
